{
    "prepare_queue": {
        "installed": [],
        "uninstalled": []
    },
    "config_munge": {
        "files": {
            "framework": {
                "parents": {
                    "ImageIO.framework": [
                        {
                            "xml": true,
                            "count": 1
                        }
                    ],
                    "CoreLocation.framework": [
                        {
                            "xml": false,
                            "count": 2
                        }
                    ],
                    "CoreGraphics.framework": [
                        {
                            "xml": false,
                            "count": 3
                        }
                    ],
                    "AssetsLibrary.framework": [
                        {
                            "xml": false,
                            "count": 3
                        }
                    ],
                    "MobileCoreServices.framework": [
                        {
                            "xml": false,
                            "count": 2
                        }
                    ],
                    "AVFoundation.framework": [
                        {
                            "xml": false,
                            "count": 1
                        }
                    ],
                    "SystemConfiguration.framework": [
                        {
                            "xml": false,
                            "count": 1
                        },
                        {
                            "xml": true,
                            "count": 1
                        }
                    ],
                    "CoreData.framework": [
                        {
                            "xml": false,
                            "count": 1
                        }
                    ],
                    "libz.dylib": [
                        {
                            "xml": false,
                            "count": 1
                        }
                    ],
                    "libsqlite3.0.dylib": [
                        {
                            "xml": false,
                            "count": 1
                        }
                    ]
                }
            },
            "config.xml": {
                "parents": {
                    "/*": [
                        {
                            "xml": "<feature name=\"Camera\"><param name=\"ios-package\" value=\"CDVCamera\" /></feature>",
                            "count": 1
                        },
                        {
                            "xml": "<preference name=\"CameraUsesGeolocation\" value=\"false\" />",
                            "count": 1
                        },
                        {
                            "xml": "<feature name=\"Device\"><param name=\"ios-package\" value=\"CDVDevice\" /></feature>",
                            "count": 1
                        },
                        {
                            "xml": "<feature name=\"File\"><param name=\"ios-package\" value=\"CDVFile\" /><param name=\"onload\" value=\"true\" /></feature>",
                            "count": 1
                        },
                        {
                            "xml": "<feature name=\"FileTransfer\"><param name=\"ios-package\" value=\"CDVFileTransfer\" /></feature>",
                            "count": 1
                        },
                        {
                            "xml": "<feature name=\"Geolocation\"><param name=\"ios-package\" value=\"CDVLocation\" /></feature>",
                            "count": 1
                        },
                        {
                            "xml": "<feature name=\"UniversalAnalytics\"><param name=\"ios-package\" value=\"UniversalAnalyticsPlugin\" /></feature>",
                            "count": 1
                        },
                        {
                            "xml": "<feature name=\"NetworkStatus\"><param name=\"ios-package\" value=\"CDVConnection\" /></feature>",
                            "count": 1
                        },
                        {
                            "xml": "<feature name=\"SplashScreen\"><param name=\"ios-package\" value=\"CDVSplashScreen\" /><param name=\"onload\" value=\"true\" /></feature>",
                            "count": 1
                        },
                        {
                            "xml": "<feature name=\"StatusBar\"><param name=\"ios-package\" value=\"CDVStatusBar\" /><param name=\"onload\" value=\"true\" /></feature>",
                            "count": 1
                        },
                        {
                            "xml": "<preference name=\"StatusBarOverlaysWebView\" value=\"true\" />",
                            "count": 1
                        },
                        {
                            "xml": "<preference name=\"StatusBarStyle\" value=\"lightcontent\" />",
                            "count": 1
                        }
                    ]
                }
            },
            "*-Info.plist": {
                "parents": {
                    "NSLocationWhenInUseUsageDescription": [
                        {
                            "xml": "<string />",
                            "count": 2
                        }
                    ]
                }
            }
        }
    },
    "installed_plugins": {
        "cordova-plugin-camera": {
            "PACKAGE_NAME": "cr.go.curridabat.YoAlcalde"
        },
        "cordova-plugin-device": {
            "PACKAGE_NAME": "cr.go.curridabat.YoAlcalde"
        },
        "cordova-plugin-file": {
            "PACKAGE_NAME": "cr.go.curridabat.YoAlcalde"
        },
        "cordova-plugin-file-transfer": {
            "PACKAGE_NAME": "cr.go.curridabat.YoAlcalde"
        },
        "cordova-plugin-geolocation": {
            "PACKAGE_NAME": "cr.go.curridabat.YoAlcalde"
        },
        "cordova-plugin-google-analytics": {
            "PACKAGE_NAME": "cr.go.curridabat.YoAlcalde"
        },
        "cordova-plugin-network-information": {
            "PACKAGE_NAME": "cr.go.curridabat.YoAlcalde"
        },
        "cordova-plugin-splashscreen": {
            "PACKAGE_NAME": "cr.go.curridabat.YoAlcalde"
        },
        "cordova-plugin-statusbar": {
            "PACKAGE_NAME": "cr.go.curridabat.YoAlcalde"
        },
        "cordova-plugin-whitelist": {
            "PACKAGE_NAME": "cr.go.curridabat.YoAlcalde"
        }
    },
    "dependent_plugins": {}
}